greenrpc
